passwords/__init__.py
passwords/auth_password_validators.py
passwords/fields.py
passwords/models.py
passwords/validators.py
passwords/locale/bg/LC_MESSAGES/django.mo
passwords/locale/bg/LC_MESSAGES/django.po
passwords/locale/de/LC_MESSAGES/django.mo
passwords/locale/de/LC_MESSAGES/django.po
passwords/locale/en/LC_MESSAGES/django.mo
passwords/locale/en/LC_MESSAGES/django.po
passwords/locale/es/LC_MESSAGES/django.mo
passwords/locale/es/LC_MESSAGES/django.po
passwords/locale/es_AR/LC_MESSAGES/django.mo
passwords/locale/es_AR/LC_MESSAGES/django.po
passwords/locale/fr/LC_MESSAGES/django.mo
passwords/locale/fr/LC_MESSAGES/django.po
passwords/locale/ja/LC_MESSAGES/django.mo
passwords/locale/ja/LC_MESSAGES/django.po
passwords/locale/pl/LC_MESSAGES/django.mo
passwords/locale/pl/LC_MESSAGES/django.po
passwords/locale/pt_BR/LC_MESSAGES/django.mo
passwords/locale/pt_BR/LC_MESSAGES/django.po
passwords/locale/pt_PT/LC_MESSAGES/django.mo
passwords/locale/pt_PT/LC_MESSAGES/django.po
passwords/locale/ru/LC_MESSAGES/django.mo
passwords/locale/ru/LC_MESSAGES/django.po
passwords/locale/tr/LC_MESSAGES/django.mo
passwords/locale/tr/LC_MESSAGES/django.po
passwords/locale/zh_CN/LC_MESSAGES/django.mo
passwords/locale/zh_CN/LC_MESSAGES/django.po
django_strong_passwords-0.1.2.dist-info/LICENSE
django_strong_passwords-0.1.2.dist-info/METADATA
django_strong_passwords-0.1.2.dist-info/WHEEL
django_strong_passwords-0.1.2.dist-info/top_level.txt
django_strong_passwords-0.1.2.dist-info/RECORD
