Metadata-Version: 2.1
Name: django-strong-passwords
Version: 0.1.2
Summary: A Django reusable app that provides validators and a form field that checks the strength of a password
Home-page: https://github.com/brhelwig/django-strong-passwords/
Author: Brandon Helwig
Author-email: django-strong-passwords@brandonhelwig.com
License: BSD
Classifier: Development Status :: 4 - Beta
Classifier: Environment :: Web Environment
Classifier: Intended Audience :: Developers
Classifier: License :: OSI Approved :: BSD License
Classifier: Operating System :: OS Independent
Classifier: Programming Language :: Python :: 2.6
Classifier: Programming Language :: Python :: 2.7
Classifier: Programming Language :: Python :: 3.4
Classifier: Programming Language :: Python :: 3.5
Classifier: Topic :: Utilities
Classifier: Framework :: Django
License-File: LICENSE
Requires-Dist: Django >=3.2
